pyramid_ratchet
